[
    {
        "category": "constellation",
        "id": 20000063,
        "name": "GJH-1C",
        "systems": [
            {
                "category": "solar_system",
                "id": 30000433,
                "name": "WU-FHQ",
                "npc_kills": 0,
                "ship_kills": 0,
                "pod_kills": 0
            },
            {
                "category": "solar_system",
                "id": 30000434,
                "name": "V-4DBR",
                "npc_kills": 0,
                "ship_kills": 0,
                "pod_kills": 0
            },
            {
                "category": "solar_system",
                "id": 30000435,
                "name": "B-5UFY",
                "npc_kills": 0,
                "ship_kills": 0,
                "pod_kills": 0
            },
            {
                "category": "solar_system",
                "id": 30000436,
                "name": "SK42-F",
                "npc_kills": 0,
                "ship_kills": 0,
                "pod_kills": 0
            },
            {
                "category": "solar_system",
                "id": 30000437,
                "name": "EU9-J3",
                "npc_kills": 152,
                "ship_kills": 0,
                "pod_kills": 0
            },
            {
                "category": "solar_system",
                "id": 30000438,
                "name": "PQRE-W",
                "npc_kills": 0,
                "ship_kills": 0,
                "pod_kills": 0
            },
            {
                "category": "solar_system",
                "id": 30000439,
                "name": "OEG-K9",
                "npc_kills": 0,
                "ship_kills": 0,
                "pod_kills": 0
            }
        ],
        "systems_count": 7,
        "total_kills_nps": 152,
        "total_kills_ship": 0,
        "total_kills_pod": 0
    },
    {
        "category": "constellation",
        "id": 20000064,
        "name": "RFQ-8Y",
        "systems": [
            {
                "category": "solar_system",
                "id": 30000440,
                "name": "0-W778",
                "npc_kills": 0,
                "ship_kills": 0,
                "pod_kills": 0
            },
            {
                "category": "solar_system",
                "id": 30000441,
                "name": "DG-8VJ",
                "npc_kills": 0,
                "ship_kills": 0,
                "pod_kills": 0
            },
            {
                "category": "solar_system",
                "id": 30000442,
                "name": "5J4K-9",
                "npc_kills": 0,
                "ship_kills": 0,
                "pod_kills": 0
            },
            {
                "category": "solar_system",
                "id": 30000443,
                "name": "MD-0AW",
                "npc_kills": 0,
                "ship_kills": 0,
                "pod_kills": 0
            },
            {
                "category": "solar_system",
                "id": 30000444,
                "name": "H-FGJO",
                "npc_kills": 0,
                "ship_kills": 0,
                "pod_kills": 0
            },
            {
                "category": "solar_system",
                "id": 30000445,
                "name": "1KAW-T",
                "npc_kills": 0,
                "ship_kills": 0,
                "pod_kills": 0
            }
        ],
        "systems_count": 6,
        "total_kills_nps": 0,
        "total_kills_ship": 0,
        "total_kills_pod": 0
    },
    {
        "category": "constellation",
        "id": 20000065,
        "name": "MZ-PA2",
        "systems": [
            {
                "category": "solar_system",
                "id": 30000446,
                "name": "C5-SUU",
                "npc_kills": 0,
                "ship_kills": 0,
                "pod_kills": 0
            },
            {
                "category": "solar_system",
                "id": 30000447,
                "name": "XSUD-1",
                "npc_kills": 0,
                "ship_kills": 0,
                "pod_kills": 0
            },
            {
                "category": "solar_system",
                "id": 30000448,
                "name": "3-LJW3",
                "npc_kills": 0,
                "ship_kills": 0,
                "pod_kills": 0
            },
            {
                "category": "solar_system",
                "id": 30000449,
                "name": "ZLO3-V",
                "npc_kills": 0,
                "ship_kills": 0,
                "pod_kills": 0
            },
            {
                "category": "solar_system",
                "id": 30000450,
                "name": "P7MI-T",
                "npc_kills": 0,
                "ship_kills": 0,
                "pod_kills": 0
            },
            {
                "category": "solar_system",
                "id": 30000451,
                "name": "JFV-ID",
                "npc_kills": 0,
                "ship_kills": 0,
                "pod_kills": 0
            },
            {
                "category": "solar_system",
                "id": 30000452,
                "name": "3-3EZB",
                "npc_kills": 0,
                "ship_kills": 0,
                "pod_kills": 0
            },
            {
                "category": "solar_system",
                "id": 30000453,
                "name": "52CW-6",
                "npc_kills": 0,
                "ship_kills": 0,
                "pod_kills": 0
            }
        ],
        "systems_count": 8,
        "total_kills_nps": 0,
        "total_kills_ship": 0,
        "total_kills_pod": 0
    },
    {
        "category": "constellation",
        "id": 20000066,
        "name": "5F8-PZ",
        "systems": [
            {
                "category": "solar_system",
                "id": 30000454,
                "name": "9-OUGJ",
                "npc_kills": 0,
                "ship_kills": 0,
                "pod_kills": 0
            },
            {
                "category": "solar_system",
                "id": 30000455,
                "name": "4NDT-W",
                "npc_kills": 0,
                "ship_kills": 0,
                "pod_kills": 0
            },
            {
                "category": "solar_system",
                "id": 30000456,
                "name": "GR-X26",
                "npc_kills": 0,
                "ship_kills": 0,
                "pod_kills": 0
            },
            {
                "category": "solar_system",
                "id": 30000457,
                "name": "6OU9-U",
                "npc_kills": 22,
                "ship_kills": 0,
                "pod_kills": 0
            },
            {
                "category": "solar_system",
                "id": 30000458,
                "name": "9N-0HF",
                "npc_kills": 0,
                "ship_kills": 0,
                "pod_kills": 0
            },
            {
                "category": "solar_system",
                "id": 30000459,
                "name": "U-OVFR",
                "npc_kills": 0,
                "ship_kills": 0,
                "pod_kills": 0
            }
        ],
        "systems_count": 6,
        "total_kills_nps": 22,
        "total_kills_ship": 0,
        "total_kills_pod": 0
    },
    {
        "category": "constellation",
        "id": 20000067,
        "name": "PR-ACX",
        "systems": [
            {
                "category": "solar_system",
                "id": 30000460,
                "name": "G3D-ZT",
                "npc_kills": 0,
                "ship_kills": 0,
                "pod_kills": 0
            },
            {
                "category": "solar_system",
                "id": 30000461,
                "name": "D-0UI0",
                "npc_kills": 0,
                "ship_kills": 0,
                "pod_kills": 0
            },
            {
                "category": "solar_system",
                "id": 30000462,
                "name": "L8-WNE",
                "npc_kills": 0,
                "ship_kills": 0,
                "pod_kills": 0
            },
            {
                "category": "solar_system",
                "id": 30000463,
                "name": "1-GBVE",
                "npc_kills": 0,
                "ship_kills": 0,
                "pod_kills": 0
            },
            {
                "category": "solar_system",
                "id": 30000464,
                "name": "GC-LTF",
                "npc_kills": 0,
                "ship_kills": 0,
                "pod_kills": 0
            },
            {
                "category": "solar_system",
                "id": 30000465,
                "name": "NB-ALM",
                "npc_kills": 0,
                "ship_kills": 0,
                "pod_kills": 0
            }
        ],
        "systems_count": 6,
        "total_kills_nps": 0,
        "total_kills_ship": 0,
        "total_kills_pod": 0
    },
    {
        "category": "constellation",
        "id": 20000068,
        "name": "5P4-QA",
        "systems": [
            {
                "category": "solar_system",
                "id": 30000466,
                "name": "LT-XI4",
                "npc_kills": 0,
                "ship_kills": 0,
                "pod_kills": 0
            },
            {
                "category": "solar_system",
                "id": 30000467,
                "name": "L-QQ6P",
                "npc_kills": 0,
                "ship_kills": 0,
                "pod_kills": 0
            },
            {
                "category": "solar_system",
                "id": 30000468,
                "name": "5OJ-G2",
                "npc_kills": 0,
                "ship_kills": 0,
                "pod_kills": 0
            },
            {
                "category": "solar_system",
                "id": 30000469,
                "name": "9-02G0",
                "npc_kills": 0,
                "ship_kills": 0,
                "pod_kills": 0
            },
            {
                "category": "solar_system",
                "id": 30000470,
                "name": "XA5-TY",
                "npc_kills": 0,
                "ship_kills": 0,
                "pod_kills": 0
            },
            {
                "category": "solar_system",
                "id": 30000471,
                "name": "M-XUZZ",
                "npc_kills": 0,
                "ship_kills": 0,
                "pod_kills": 0
            }
        ],
        "systems_count": 6,
        "total_kills_nps": 0,
        "total_kills_ship": 0,
        "total_kills_pod": 0
    },
    {
        "category": "constellation",
        "id": 20000069,
        "name": "1RG-GU",
        "systems": [
            {
                "category": "solar_system",
                "id": 30000472,
                "name": "OFVH-Y",
                "npc_kills": 0,
                "ship_kills": 0,
                "pod_kills": 0
            },
            {
                "category": "solar_system",
                "id": 30000473,
                "name": "2-X0PF",
                "npc_kills": 0,
                "ship_kills": 0,
                "pod_kills": 0
            },
            {
                "category": "solar_system",
                "id": 30000474,
                "name": "1-PGSG",
                "npc_kills": 0,
                "ship_kills": 0,
                "pod_kills": 0
            },
            {
                "category": "solar_system",
                "id": 30000475,
                "name": "QLPX-J",
                "npc_kills": 0,
                "ship_kills": 0,
                "pod_kills": 0
            },
            {
                "category": "solar_system",
                "id": 30000476,
                "name": "A-C5TC",
                "npc_kills": 0,
                "ship_kills": 0,
                "pod_kills": 0
            },
            {
                "category": "solar_system",
                "id": 30000477,
                "name": "RZ-PIY",
                "npc_kills": 0,
                "ship_kills": 0,
                "pod_kills": 0
            },
            {
                "category": "solar_system",
                "id": 30000478,
                "name": "FR46-E",
                "npc_kills": 0,
                "ship_kills": 0,
                "pod_kills": 0
            }
        ],
        "systems_count": 7,
        "total_kills_nps": 0,
        "total_kills_ship": 0,
        "total_kills_pod": 0
    },
    {
        "category": "constellation",
        "id": 20000070,
        "name": "ZPI-2E",
        "systems": [
            {
                "category": "solar_system",
                "id": 30000479,
                "name": "SLVP-D",
                "npc_kills": 0,
                "ship_kills": 0,
                "pod_kills": 0
            },
            {
                "category": "solar_system",
                "id": 30000480,
                "name": "0-G8NO",
                "npc_kills": 89,
                "ship_kills": 0,
                "pod_kills": 0
            },
            {
                "category": "solar_system",
                "id": 30000481,
                "name": "QRFJ-Q",
                "npc_kills": 21,
                "ship_kills": 0,
                "pod_kills": 0
            },
            {
                "category": "solar_system",
                "id": 30000482,
                "name": "HZFJ-M",
                "npc_kills": 0,
                "ship_kills": 0,
                "pod_kills": 0
            },
            {
                "category": "solar_system",
                "id": 30000483,
                "name": "77S8-E",
                "npc_kills": 0,
                "ship_kills": 0,
                "pod_kills": 0
            },
            {
                "category": "solar_system",
                "id": 30000484,
                "name": "FMH-OV",
                "npc_kills": 0,
                "ship_kills": 0,
                "pod_kills": 0
            }
        ],
        "systems_count": 6,
        "total_kills_nps": 110,
        "total_kills_ship": 0,
        "total_kills_pod": 0
    },
    {
        "category": "constellation",
        "id": 20000071,
        "name": "D-95MV",
        "systems": [
            {
                "category": "solar_system",
                "id": 30000485,
                "name": "TYB-69",
                "npc_kills": 0,
                "ship_kills": 0,
                "pod_kills": 0
            },
            {
                "category": "solar_system",
                "id": 30000486,
                "name": "EDQG-L",
                "npc_kills": 66,
                "ship_kills": 0,
                "pod_kills": 0
            },
            {
                "category": "solar_system",
                "id": 30000487,
                "name": "7-P1JO",
                "npc_kills": 0,
                "ship_kills": 0,
                "pod_kills": 0
            },
            {
                "category": "solar_system",
                "id": 30000488,
                "name": "T-0JWP",
                "npc_kills": 0,
                "ship_kills": 0,
                "pod_kills": 0
            },
            {
                "category": "solar_system",
                "id": 30000489,
                "name": "J-L9MA",
                "npc_kills": 0,
                "ship_kills": 0,
                "pod_kills": 0
            },
            {
                "category": "solar_system",
                "id": 30000490,
                "name": "DX-TAR",
                "npc_kills": 0,
                "ship_kills": 0,
                "pod_kills": 0
            },
            {
                "category": "solar_system",
                "id": 30000491,
                "name": "A-7XFN",
                "npc_kills": 0,
                "ship_kills": 0,
                "pod_kills": 0
            },
            {
                "category": "solar_system",
                "id": 30000492,
                "name": "O3-4MN",
                "npc_kills": 0,
                "ship_kills": 0,
                "pod_kills": 0
            },
            {
                "category": "solar_system",
                "id": 30000493,
                "name": "U-MFTL",
                "npc_kills": 0,
                "ship_kills": 0,
                "pod_kills": 0
            }
        ],
        "systems_count": 9,
        "total_kills_nps": 66,
        "total_kills_ship": 0,
        "total_kills_pod": 0
    },
    {
        "category": "constellation",
        "id": 20000072,
        "name": "3R-BJL",
        "systems": [
            {
                "category": "solar_system",
                "id": 30000494,
                "name": "8FN-GP",
                "npc_kills": 0,
                "ship_kills": 0,
                "pod_kills": 0
            },
            {
                "category": "solar_system",
                "id": 30000495,
                "name": "FIDY-8",
                "npc_kills": 0,
                "ship_kills": 0,
                "pod_kills": 0
            },
            {
                "category": "solar_system",
                "id": 30000496,
                "name": "X40H-9",
                "npc_kills": 0,
                "ship_kills": 0,
                "pod_kills": 0
            },
            {
                "category": "solar_system",
                "id": 30000497,
                "name": "F2W-C6",
                "npc_kills": 0,
                "ship_kills": 0,
                "pod_kills": 0
            },
            {
                "category": "solar_system",
                "id": 30000498,
                "name": "KZ9T-C",
                "npc_kills": 0,
                "ship_kills": 0,
                "pod_kills": 0
            },
            {
                "category": "solar_system",
                "id": 30000499,
                "name": "XW2H-V",
                "npc_kills": 0,
                "ship_kills": 0,
                "pod_kills": 0
            }
        ],
        "systems_count": 6,
        "total_kills_nps": 0,
        "total_kills_ship": 0,
        "total_kills_pod": 0
    },
    {
        "category": "constellation",
        "id": 20000073,
        "name": "T875-C",
        "systems": [
            {
                "category": "solar_system",
                "id": 30000500,
                "name": "F9O-U9",
                "npc_kills": 0,
                "ship_kills": 0,
                "pod_kills": 0
            },
            {
                "category": "solar_system",
                "id": 30000501,
                "name": "S-51XG",
                "npc_kills": 0,
                "ship_kills": 0,
                "pod_kills": 0
            },
            {
                "category": "solar_system",
                "id": 30000502,
                "name": "E-1XVP",
                "npc_kills": 0,
                "ship_kills": 0,
                "pod_kills": 0
            },
            {
                "category": "solar_system",
                "id": 30000503,
                "name": "E-ACV6",
                "npc_kills": 0,
                "ship_kills": 0,
                "pod_kills": 0
            },
            {
                "category": "solar_system",
                "id": 30000504,
                "name": "BOZ1-O",
                "npc_kills": 0,
                "ship_kills": 0,
                "pod_kills": 0
            },
            {
                "category": "solar_system",
                "id": 30000505,
                "name": "QIMO-2",
                "npc_kills": 0,
                "ship_kills": 0,
                "pod_kills": 0
            },
            {
                "category": "solar_system",
                "id": 30000506,
                "name": "Z-2Y2Y",
                "npc_kills": 42,
                "ship_kills": 0,
                "pod_kills": 0
            },
            {
                "category": "solar_system",
                "id": 30000507,
                "name": "Q0J-RH",
                "npc_kills": 3,
                "ship_kills": 0,
                "pod_kills": 0
            }
        ],
        "systems_count": 8,
        "total_kills_nps": 45,
        "total_kills_ship": 0,
        "total_kills_pod": 0
    },
    {
        "category": "constellation",
        "id": 20000074,
        "name": "4SRW-B",
        "systems": [
            {
                "category": "solar_system",
                "id": 30000508,
                "name": "SAI-T9",
                "npc_kills": 4,
                "ship_kills": 0,
                "pod_kills": 0
            },
            {
                "category": "solar_system",
                "id": 30000509,
                "name": "IAS-I5",
                "npc_kills": 0,
                "ship_kills": 0,
                "pod_kills": 0
            },
            {
                "category": "solar_system",
                "id": 30000510,
                "name": "K7S-FF",
                "npc_kills": 0,
                "ship_kills": 0,
                "pod_kills": 0
            },
            {
                "category": "solar_system",
                "id": 30000511,
                "name": "RT-9WL",
                "npc_kills": 0,
                "ship_kills": 0,
                "pod_kills": 0
            },
            {
                "category": "solar_system",
                "id": 30000512,
                "name": "O5Q7-U",
                "npc_kills": 0,
                "ship_kills": 0,
                "pod_kills": 0
            },
            {
                "category": "solar_system",
                "id": 30000513,
                "name": "62O-UE",
                "npc_kills": 0,
                "ship_kills": 0,
                "pod_kills": 0
            }
        ],
        "systems_count": 6,
        "total_kills_nps": 4,
        "total_kills_ship": 0,
        "total_kills_pod": 0
    },
    {
        "category": "constellation",
        "id": 20000075,
        "name": "HOV-VI",
        "systems": [
            {
                "category": "solar_system",
                "id": 30000514,
                "name": "U0W-DR",
                "npc_kills": 0,
                "ship_kills": 0,
                "pod_kills": 0
            },
            {
                "category": "solar_system",
                "id": 30000515,
                "name": "SY-UWN",
                "npc_kills": 0,
                "ship_kills": 0,
                "pod_kills": 0
            },
            {
                "category": "solar_system",
                "id": 30000516,
                "name": "DX-DFJ",
                "npc_kills": 0,
                "ship_kills": 0,
                "pod_kills": 0
            },
            {
                "category": "solar_system",
                "id": 30000517,
                "name": "X-31TE",
                "npc_kills": 0,
                "ship_kills": 0,
                "pod_kills": 0
            },
            {
                "category": "solar_system",
                "id": 30000518,
                "name": "DVWV-3",
                "npc_kills": 0,
                "ship_kills": 0,
                "pod_kills": 0
            },
            {
                "category": "solar_system",
                "id": 30000519,
                "name": "KE-0FB",
                "npc_kills": 0,
                "ship_kills": 0,
                "pod_kills": 0
            },
            {
                "category": "solar_system",
                "id": 30000520,
                "name": "I-9GI1",
                "npc_kills": 4,
                "ship_kills": 0,
                "pod_kills": 0
            }
        ],
        "systems_count": 7,
        "total_kills_nps": 4,
        "total_kills_ship": 0,
        "total_kills_pod": 0
    },
    {
        "category": "constellation",
        "id": 20000076,
        "name": "NZU8-G",
        "systems": [
            {
                "category": "solar_system",
                "id": 30000521,
                "name": "W6P-7U",
                "npc_kills": 0,
                "ship_kills": 0,
                "pod_kills": 0
            },
            {
                "category": "solar_system",
                "id": 30000522,
                "name": "0IF-26",
                "npc_kills": 0,
                "ship_kills": 0,
                "pod_kills": 0
            },
            {
                "category": "solar_system",
                "id": 30000523,
                "name": "H-93YV",
                "npc_kills": 0,
                "ship_kills": 0,
                "pod_kills": 0
            },
            {
                "category": "solar_system",
                "id": 30000524,
                "name": "E51-JE",
                "npc_kills": 81,
                "ship_kills": 0,
                "pod_kills": 0
            },
            {
                "category": "solar_system",
                "id": 30000525,
                "name": "7-A6XV",
                "npc_kills": 0,
                "ship_kills": 0,
                "pod_kills": 0
            },
            {
                "category": "solar_system",
                "id": 30000526,
                "name": "QXE-1N",
                "npc_kills": 106,
                "ship_kills": 0,
                "pod_kills": 0
            },
            {
                "category": "solar_system",
                "id": 30000527,
                "name": "U69-YC",
                "npc_kills": 0,
                "ship_kills": 0,
                "pod_kills": 0
            },
            {
                "category": "solar_system",
                "id": 30000528,
                "name": "L-L7PE",
                "npc_kills": 0,
                "ship_kills": 0,
                "pod_kills": 0
            }
        ],
        "systems_count": 8,
        "total_kills_nps": 187,
        "total_kills_ship": 0,
        "total_kills_pod": 0
    }
]