[
    {
        "category": "constellation",
        "id": 21000265,
        "name": "E-C00265",
        "systems": [
            {
                "category": "solar_system",
                "id": 31002126,
                "name": "J162753",
                "npc_kills": 0,
                "ship_kills": 0,
                "pod_kills": 0
            },
            {
                "category": "solar_system",
                "id": 31002128,
                "name": "J125254",
                "npc_kills": 0,
                "ship_kills": 0,
                "pod_kills": 0
            },
            {
                "category": "solar_system",
                "id": 31002131,
                "name": "J120437",
                "npc_kills": 0,
                "ship_kills": 0,
                "pod_kills": 0
            },
            {
                "category": "solar_system",
                "id": 31002127,
                "name": "J135301",
                "npc_kills": 0,
                "ship_kills": 0,
                "pod_kills": 0
            },
            {
                "category": "solar_system",
                "id": 31002129,
                "name": "J145320",
                "npc_kills": 0,
                "ship_kills": 0,
                "pod_kills": 0
            },
            {
                "category": "solar_system",
                "id": 31002130,
                "name": "J103116",
                "npc_kills": 0,
                "ship_kills": 0,
                "pod_kills": 0
            },
            {
                "category": "solar_system",
                "id": 31002132,
                "name": "J100252",
                "npc_kills": 0,
                "ship_kills": 0,
                "pod_kills": 0
            },
            {
                "category": "solar_system",
                "id": 31002133,
                "name": "J153919",
                "npc_kills": 0,
                "ship_kills": 0,
                "pod_kills": 0
            },
            {
                "category": "solar_system",
                "id": 31002490,
                "name": "J221356",
                "npc_kills": 0,
                "ship_kills": 0,
                "pod_kills": 0
            }
        ],
        "systems_count": 9,
        "total_kills_nps": 0,
        "total_kills_ship": 0,
        "total_kills_pod": 0
    },
    {
        "category": "constellation",
        "id": 21000266,
        "name": "E-C00266",
        "systems": [
            {
                "category": "solar_system",
                "id": 31002138,
                "name": "J131549",
                "npc_kills": 0,
                "ship_kills": 0,
                "pod_kills": 0
            },
            {
                "category": "solar_system",
                "id": 31002139,
                "name": "J205517",
                "npc_kills": 0,
                "ship_kills": 0,
                "pod_kills": 0
            },
            {
                "category": "solar_system",
                "id": 31002136,
                "name": "J115933",
                "npc_kills": 0,
                "ship_kills": 0,
                "pod_kills": 0
            },
            {
                "category": "solar_system",
                "id": 31002137,
                "name": "J133529",
                "npc_kills": 0,
                "ship_kills": 0,
                "pod_kills": 0
            },
            {
                "category": "solar_system",
                "id": 31002134,
                "name": "J115520",
                "npc_kills": 0,
                "ship_kills": 0,
                "pod_kills": 0
            },
            {
                "category": "solar_system",
                "id": 31002135,
                "name": "J100919",
                "npc_kills": 0,
                "ship_kills": 0,
                "pod_kills": 0
            }
        ],
        "systems_count": 6,
        "total_kills_nps": 0,
        "total_kills_ship": 0,
        "total_kills_pod": 0
    },
    {
        "category": "constellation",
        "id": 21000267,
        "name": "E-C00267",
        "systems": [
            {
                "category": "solar_system",
                "id": 31002144,
                "name": "J172937",
                "npc_kills": 0,
                "ship_kills": 0,
                "pod_kills": 0
            },
            {
                "category": "solar_system",
                "id": 31002145,
                "name": "J122757",
                "npc_kills": 0,
                "ship_kills": 0,
                "pod_kills": 0
            },
            {
                "category": "solar_system",
                "id": 31002140,
                "name": "J220546",
                "npc_kills": 0,
                "ship_kills": 0,
                "pod_kills": 0
            },
            {
                "category": "solar_system",
                "id": 31002141,
                "name": "J102853",
                "npc_kills": 0,
                "ship_kills": 0,
                "pod_kills": 0
            },
            {
                "category": "solar_system",
                "id": 31002142,
                "name": "J115418",
                "npc_kills": 0,
                "ship_kills": 0,
                "pod_kills": 0
            },
            {
                "category": "solar_system",
                "id": 31002143,
                "name": "J155040",
                "npc_kills": 0,
                "ship_kills": 0,
                "pod_kills": 0
            }
        ],
        "systems_count": 6,
        "total_kills_nps": 0,
        "total_kills_ship": 0,
        "total_kills_pod": 0
    },
    {
        "category": "constellation",
        "id": 21000268,
        "name": "E-C00268",
        "systems": [
            {
                "category": "solar_system",
                "id": 31002153,
                "name": "J162047",
                "npc_kills": 0,
                "ship_kills": 0,
                "pod_kills": 0
            },
            {
                "category": "solar_system",
                "id": 31002146,
                "name": "J100759",
                "npc_kills": 0,
                "ship_kills": 0,
                "pod_kills": 0
            },
            {
                "category": "solar_system",
                "id": 31002147,
                "name": "J145416",
                "npc_kills": 0,
                "ship_kills": 0,
                "pod_kills": 0
            },
            {
                "category": "solar_system",
                "id": 31002148,
                "name": "J152034",
                "npc_kills": 0,
                "ship_kills": 0,
                "pod_kills": 0
            },
            {
                "category": "solar_system",
                "id": 31002149,
                "name": "J125544",
                "npc_kills": 0,
                "ship_kills": 0,
                "pod_kills": 0
            },
            {
                "category": "solar_system",
                "id": 31002150,
                "name": "J123235",
                "npc_kills": 0,
                "ship_kills": 0,
                "pod_kills": 0
            },
            {
                "category": "solar_system",
                "id": 31002151,
                "name": "J151204",
                "npc_kills": 0,
                "ship_kills": 0,
                "pod_kills": 0
            },
            {
                "category": "solar_system",
                "id": 31002152,
                "name": "J104537",
                "npc_kills": 0,
                "ship_kills": 0,
                "pod_kills": 0
            },
            {
                "category": "solar_system",
                "id": 31002154,
                "name": "J140514",
                "npc_kills": 0,
                "ship_kills": 0,
                "pod_kills": 0
            },
            {
                "category": "solar_system",
                "id": 31002504,
                "name": "J125657",
                "npc_kills": 0,
                "ship_kills": 0,
                "pod_kills": 0
            }
        ],
        "systems_count": 10,
        "total_kills_nps": 0,
        "total_kills_ship": 0,
        "total_kills_pod": 0
    },
    {
        "category": "constellation",
        "id": 21000269,
        "name": "E-C00269",
        "systems": [
            {
                "category": "solar_system",
                "id": 31002161,
                "name": "J101556",
                "npc_kills": 0,
                "ship_kills": 0,
                "pod_kills": 0
            },
            {
                "category": "solar_system",
                "id": 31002499,
                "name": "J143605",
                "npc_kills": 0,
                "ship_kills": 0,
                "pod_kills": 0
            },
            {
                "category": "solar_system",
                "id": 31002155,
                "name": "J154152",
                "npc_kills": 0,
                "ship_kills": 0,
                "pod_kills": 0
            },
            {
                "category": "solar_system",
                "id": 31002156,
                "name": "J143626",
                "npc_kills": 0,
                "ship_kills": 0,
                "pod_kills": 0
            },
            {
                "category": "solar_system",
                "id": 31002157,
                "name": "J161737",
                "npc_kills": 0,
                "ship_kills": 0,
                "pod_kills": 0
            },
            {
                "category": "solar_system",
                "id": 31002158,
                "name": "J142110",
                "npc_kills": 0,
                "ship_kills": 0,
                "pod_kills": 0
            },
            {
                "category": "solar_system",
                "id": 31002159,
                "name": "J112042",
                "npc_kills": 0,
                "ship_kills": 0,
                "pod_kills": 0
            },
            {
                "category": "solar_system",
                "id": 31002160,
                "name": "J105719",
                "npc_kills": 0,
                "ship_kills": 0,
                "pod_kills": 0
            },
            {
                "category": "solar_system",
                "id": 31002162,
                "name": "J230047",
                "npc_kills": 0,
                "ship_kills": 0,
                "pod_kills": 0
            },
            {
                "category": "solar_system",
                "id": 31002163,
                "name": "J213226",
                "npc_kills": 0,
                "ship_kills": 0,
                "pod_kills": 0
            }
        ],
        "systems_count": 10,
        "total_kills_nps": 0,
        "total_kills_ship": 0,
        "total_kills_pod": 0
    },
    {
        "category": "constellation",
        "id": 21000270,
        "name": "E-C00270",
        "systems": [
            {
                "category": "solar_system",
                "id": 31002164,
                "name": "J104218",
                "npc_kills": 0,
                "ship_kills": 0,
                "pod_kills": 0
            },
            {
                "category": "solar_system",
                "id": 31002168,
                "name": "J105135",
                "npc_kills": 0,
                "ship_kills": 0,
                "pod_kills": 0
            },
            {
                "category": "solar_system",
                "id": 31002169,
                "name": "J111818",
                "npc_kills": 0,
                "ship_kills": 0,
                "pod_kills": 0
            },
            {
                "category": "solar_system",
                "id": 31002170,
                "name": "J110841",
                "npc_kills": 0,
                "ship_kills": 0,
                "pod_kills": 0
            },
            {
                "category": "solar_system",
                "id": 31002165,
                "name": "J115308",
                "npc_kills": 0,
                "ship_kills": 0,
                "pod_kills": 0
            },
            {
                "category": "solar_system",
                "id": 31002166,
                "name": "J140418",
                "npc_kills": 0,
                "ship_kills": 0,
                "pod_kills": 0
            },
            {
                "category": "solar_system",
                "id": 31002167,
                "name": "J101343",
                "npc_kills": 0,
                "ship_kills": 0,
                "pod_kills": 0
            }
        ],
        "systems_count": 7,
        "total_kills_nps": 0,
        "total_kills_ship": 0,
        "total_kills_pod": 0
    },
    {
        "category": "constellation",
        "id": 21000271,
        "name": "E-C00271",
        "systems": [
            {
                "category": "solar_system",
                "id": 31002171,
                "name": "J134024",
                "npc_kills": 0,
                "ship_kills": 0,
                "pod_kills": 0
            },
            {
                "category": "solar_system",
                "id": 31002176,
                "name": "J133553",
                "npc_kills": 0,
                "ship_kills": 0,
                "pod_kills": 0
            },
            {
                "category": "solar_system",
                "id": 31002177,
                "name": "J115422",
                "npc_kills": 0,
                "ship_kills": 0,
                "pod_kills": 0
            },
            {
                "category": "solar_system",
                "id": 31002172,
                "name": "J142349",
                "npc_kills": 0,
                "ship_kills": 0,
                "pod_kills": 0
            },
            {
                "category": "solar_system",
                "id": 31002173,
                "name": "J212203",
                "npc_kills": 0,
                "ship_kills": 0,
                "pod_kills": 0
            },
            {
                "category": "solar_system",
                "id": 31002174,
                "name": "J124942",
                "npc_kills": 0,
                "ship_kills": 0,
                "pod_kills": 0
            },
            {
                "category": "solar_system",
                "id": 31002175,
                "name": "J131747",
                "npc_kills": 0,
                "ship_kills": 0,
                "pod_kills": 0
            }
        ],
        "systems_count": 7,
        "total_kills_nps": 0,
        "total_kills_ship": 0,
        "total_kills_pod": 0
    },
    {
        "category": "constellation",
        "id": 21000272,
        "name": "E-C00272",
        "systems": [
            {
                "category": "solar_system",
                "id": 31002178,
                "name": "J103448",
                "npc_kills": 0,
                "ship_kills": 0,
                "pod_kills": 0
            },
            {
                "category": "solar_system",
                "id": 31002179,
                "name": "J161301",
                "npc_kills": 0,
                "ship_kills": 0,
                "pod_kills": 0
            },
            {
                "category": "solar_system",
                "id": 31002180,
                "name": "J130334",
                "npc_kills": 0,
                "ship_kills": 0,
                "pod_kills": 0
            },
            {
                "category": "solar_system",
                "id": 31002181,
                "name": "J172125",
                "npc_kills": 0,
                "ship_kills": 0,
                "pod_kills": 0
            },
            {
                "category": "solar_system",
                "id": 31002182,
                "name": "J114537",
                "npc_kills": 0,
                "ship_kills": 0,
                "pod_kills": 0
            },
            {
                "category": "solar_system",
                "id": 31002183,
                "name": "J134440",
                "npc_kills": 0,
                "ship_kills": 0,
                "pod_kills": 0
            },
            {
                "category": "solar_system",
                "id": 31002184,
                "name": "J101912",
                "npc_kills": 0,
                "ship_kills": 0,
                "pod_kills": 0
            },
            {
                "category": "solar_system",
                "id": 31002185,
                "name": "J214006",
                "npc_kills": 0,
                "ship_kills": 0,
                "pod_kills": 0
            }
        ],
        "systems_count": 8,
        "total_kills_nps": 0,
        "total_kills_ship": 0,
        "total_kills_pod": 0
    },
    {
        "category": "constellation",
        "id": 21000273,
        "name": "E-C00273",
        "systems": [
            {
                "category": "solar_system",
                "id": 31002188,
                "name": "J125641",
                "npc_kills": 0,
                "ship_kills": 0,
                "pod_kills": 0
            },
            {
                "category": "solar_system",
                "id": 31002186,
                "name": "J235108",
                "npc_kills": 0,
                "ship_kills": 0,
                "pod_kills": 0
            },
            {
                "category": "solar_system",
                "id": 31002187,
                "name": "J124538",
                "npc_kills": 0,
                "ship_kills": 0,
                "pod_kills": 0
            },
            {
                "category": "solar_system",
                "id": 31002189,
                "name": "J141728",
                "npc_kills": 0,
                "ship_kills": 0,
                "pod_kills": 0
            },
            {
                "category": "solar_system",
                "id": 31002190,
                "name": "J100616",
                "npc_kills": 0,
                "ship_kills": 0,
                "pod_kills": 0
            },
            {
                "category": "solar_system",
                "id": 31002191,
                "name": "J204350",
                "npc_kills": 0,
                "ship_kills": 0,
                "pod_kills": 0
            },
            {
                "category": "solar_system",
                "id": 31002192,
                "name": "J151300",
                "npc_kills": 0,
                "ship_kills": 0,
                "pod_kills": 0
            },
            {
                "category": "solar_system",
                "id": 31002193,
                "name": "J114041",
                "npc_kills": 0,
                "ship_kills": 0,
                "pod_kills": 0
            }
        ],
        "systems_count": 8,
        "total_kills_nps": 0,
        "total_kills_ship": 0,
        "total_kills_pod": 0
    }
]